flake8_pytest_mark/__init__.py
flake8_pytest_mark/rules.py
flake8_pytest_mark-1.1.0.dist-info/LICENSE
flake8_pytest_mark-1.1.0.dist-info/METADATA
flake8_pytest_mark-1.1.0.dist-info/WHEEL
flake8_pytest_mark-1.1.0.dist-info/entry_points.txt
flake8_pytest_mark-1.1.0.dist-info/top_level.txt
flake8_pytest_mark-1.1.0.dist-info/RECORD
