Metadata-Version: 2.1
Name: flake8-pytest-mark
Version: 1.1.0
Summary: A flake8 plugin that helps check the presence of a PyTest mark
Home-page: https://github.com/rcbops/flake8-pytest-mark
Author: rpc-automation
Author-email: rpc-automation@rackspace.com
License: Apache Software License 2.0
Keywords: flake8 flake8-pytest-mark
Platform: UNKNOWN
Classifier: Development Status :: 4 - Beta
Classifier: Framework :: Flake8
Classifier: Intended Audience :: Developers
Classifier: License :: OSI Approved :: Apache Software License
Classifier: Natural Language :: English
Classifier: Programming Language :: Python :: 2
Classifier: Programming Language :: Python :: 2.7
Classifier: Programming Language :: Python :: 3
Classifier: Programming Language :: Python :: 3.5
Classifier: Programming Language :: Python :: 3.6
Classifier: Topic :: Software Development :: Libraries :: Python Modules
Requires-Python: >=2.7, !=3.0.*, !=3.1.*, !=3.2.*, !=3.3.*
Requires-Dist: flake8 (>=3.5.0)
